dvp_components/AltBadge.py
dvp_components/App.py
dvp_components/DvpAffix.py
dvp_components/DvpButton.py
dvp_components/DvpCard.py
dvp_components/DvpCheckbox.py
dvp_components/DvpCheckboxGroup.py
dvp_components/DvpCol.py
dvp_components/DvpCollapse.py
dvp_components/DvpComponents.py
dvp_components/DvpContent.py
dvp_components/DvpDateRangePicker.py
dvp_components/DvpDescriptionItem.py
dvp_components/DvpDescriptions.py
dvp_components/DvpFooter.py
dvp_components/DvpForm.py
dvp_components/DvpFormItem.py
dvp_components/DvpHeader.py
dvp_components/DvpIcon.py
dvp_components/DvpInput.py
dvp_components/DvpInputNumber.py
dvp_components/DvpLayout.py
dvp_components/DvpMenu.py
dvp_components/DvpMultiInput.py
dvp_components/DvpPagination.py
dvp_components/DvpParagraph.py
dvp_components/DvpRadioGroup.py
dvp_components/DvpRow.py
dvp_components/DvpSelect.py
dvp_components/DvpSider.py
dvp_components/DvpSiderTemplate.py
dvp_components/DvpSlider.py
dvp_components/DvpSpace.py
dvp_components/DvpSpin.py
dvp_components/DvpSpinJJJ.py
dvp_components/DvpSpinner.py
dvp_components/DvpSwitch.py
dvp_components/DvpTable.py
dvp_components/DvpTag.py
dvp_components/DvpText.py
dvp_components/DvpTimeline.py
dvp_components/DvpTitle.py
dvp_components/ExecuteJs.py
dvp_components/RawHTML.py
dvp_components/Table.py
dvp_components/Theme.py
dvp_components/__init__.py
dvp_components/_imports_.py
dvp_components/async-DvpComponents.js
dvp_components/async-DvpComponents.js.map
dvp_components/dvp_components.min.js
dvp_components/dvp_components.min.js.map
dvp_components/metadata.json
dvp_components/package-info.json
dvp_components-0.0.2.dist-info/LICENSE
dvp_components-0.0.2.dist-info/METADATA
dvp_components-0.0.2.dist-info/WHEEL
dvp_components-0.0.2.dist-info/top_level.txt
dvp_components-0.0.2.dist-info/RECORD
